{
	"name": "F29FB Assignment Codespace",
	"image":"mcr.microsoft.com/devcontainers/python:3",
	"features": {
        "ghcr.io/michidk/devcontainers-features/typst:1": {}
    },
	"customizations": {
		"vscode": {
			"extensions": [
				// Python Extension
				"ms-python.python",
				"ms-python.pylint",
				"njpwerner.autodocstring",
				"esbenp.prettier-vscode",
				// Miscellaneous Extensions
				"VisualStudioExptTeam.vscodeintellicode",
				"VisualStudioExptTeam.intellicode-api-usage-examples",
				"ms-vscode-remote.remote-containers",
				"eamodio.gitlens", // GitLens
				"mhutchie.git-graph",
				// Markdown
				"yzhang.markdown-all-in-one",
				"bierner.github-markdown-preview",
				// Icon Pack
				"vscode-icons-team.vscode-icons",
				"myriad-dreamin.tinymist" // Typst
			]
		},
		"codespaces": {
			"openFiles": [ "README.md", "F29FB.py"]
		}
	}
}